[
    {
        "value": "zhinan",
        "label": "指南",
        "children": [
            {
                "value": "shejiyuanze",
                "label": "设计原则",
                "children": [
                    {
                        "value": "yizhi",
                        "label": "一致"
                    },
                    {
                        "value": "fankui",
                        "label": "反馈"
                    },
                    {
                        "value": "xiaolv",
                        "label": "效率"
                    },
                    {
                        "value": "kekong",
                        "label": "可控"
                    }
                ]
            }
        ]
    },
    {
        "value": "zujian",
        "label": "组件"
    },
    {
        "value": "kekong",
        "label": "可控",
        "children": null
    }
]